clockify_api_client_adgstudios/__init__.py
clockify_api_client_adgstudios/abstract_clockify.py
clockify_api_client_adgstudios/client.py
clockify_api_client_adgstudios/utils.py
clockify_api_client_adgstudios/factories/__init__.py
clockify_api_client_adgstudios/factories/abstract_factory.py
clockify_api_client_adgstudios/factories/client_factory.py
clockify_api_client_adgstudios/factories/project_factory.py
clockify_api_client_adgstudios/factories/report_factory.py
clockify_api_client_adgstudios/factories/task_factory.py
clockify_api_client_adgstudios/factories/time_entry_factory.py
clockify_api_client_adgstudios/factories/user_factory.py
clockify_api_client_adgstudios/factories/workspace_factory.py
clockify_api_client_adgstudios/models/__init__.py
clockify_api_client_adgstudios/models/client.py
clockify_api_client_adgstudios/models/project.py
clockify_api_client_adgstudios/models/report.py
clockify_api_client_adgstudios/models/task.py
clockify_api_client_adgstudios/models/time_entry.py
clockify_api_client_adgstudios/models/user.py
clockify_api_client_adgstudios/models/workspace.py
clockify_api_client_adgstudios-1.0.7.dist-info/LICENSE
clockify_api_client_adgstudios-1.0.7.dist-info/METADATA
clockify_api_client_adgstudios-1.0.7.dist-info/WHEEL
clockify_api_client_adgstudios-1.0.7.dist-info/top_level.txt
clockify_api_client_adgstudios-1.0.7.dist-info/RECORD
