Metadata-Version: 2.1
Name: clockify-api-client-adgstudios
Version: 1.0.7
Summary: Simple python API client for clockify. Inspired by https://pypi.org/project/clockify/library.
Home-page: https://github.com/eluvia-com/clockify-api-aclient
Author: Michael Bláha, Ashlin Darius Govindasamy
Author-email: michael.blaha@eluvia.com, adg@adgstudios.co.za
License: UNKNOWN
Platform: UNKNOWN
Classifier: Programming Language :: Python :: 3
Classifier: License :: OSI Approved :: MIT License
Classifier: Operating System :: OS Independent
Requires-Dist: requests
Requires-Dist: factory-boy
Provides-Extra: dev
Requires-Dist: twine ; extra == 'dev'
